{"data":{"markdownRemark":{"frontmatter":{"title":"Water Analysis","path":"src/pages/services/water-anal.md"},"html":"<p>You’re looking forward to long, lazy afternoons relaxing in the crystal clear water. Or maybe you’re planning a big pool party for friends and family. But is your pool ready? How do you know? The answer is pool water testing.</p>\n<p>Let us take care of keeping your water at the perfect balance. We monitor and add chemicals as often as needed to keep your pool in pristine condition.</p>\n<h2>Combating Contaminants</h2>\n<ul>\n<li>\n<p>Problems with your pool water can crop up due to the quality of the water you put in your pool.</p>\n</li>\n<li>\n<p>Well water contains more minerals, so you may see more copper and iron in your pool water. And if your city has hard water, the likelihood of high calcium levels is increased.</p>\n</li>\n<li>\n<p>These contaminants can make it more difficult to maintain the proper chemical balance in your pool, and they can stain and otherwise damage pool surfaces.</p>\n</li>\n<li>\n<p>Keeping an eye on them and preventing damage is more efficient and less costly than having to fix that damage later. And that prevention starts with pool water testing.</p>\n</li>\n</ul>"}},"pageContext":{"id":"3693f2e8-4196-5953-9910-fe39e9e3962d"}}